Pynapse/__init__.py
Pynapse/main.py
Pynapse-1.2.0.dist-info/METADATA
Pynapse-1.2.0.dist-info/WHEEL
Pynapse-1.2.0.dist-info/top_level.txt
Pynapse-1.2.0.dist-info/RECORD
