Metadata-Version: 2.1
Name: Pynapse
Version: 1.2.0
Requires-Dist: numpy
